eddy/__init__.py
eddy/fit_annulus.py
eddy/fit_cube.py
eddy/modelling.py
astro_eddy-1.3.4.dist-info/LICENSE.md
astro_eddy-1.3.4.dist-info/METADATA
astro_eddy-1.3.4.dist-info/WHEEL
astro_eddy-1.3.4.dist-info/top_level.txt
astro_eddy-1.3.4.dist-info/RECORD
