Metadata-Version: 2.1
Name: astro-eddy
Version: 1.3.4
Summary: Tools to recover expectionally precise rotation curves from spatially resolved spectra.
Home-page: https://github.com/richteague/eddy
Author: Richard Teague
Author-email: richard.d.teague@cfa.harvard.edu
License: MIT
Platform: UNKNOWN
Classifier: Programming Language :: Python :: 3.5
Classifier: License :: OSI Approved :: MIT License
Classifier: Operating System :: OS Independent
Requires-Dist: scipy (>=1)
Requires-Dist: numpy
Requires-Dist: matplotlib (>=3)
Requires-Dist: emcee (>=3)
Requires-Dist: corner (>=2)
